schemafied/__init__.py
schemafied/exceptions.py
schemafied/py.typed
schemafied/schema.py
schemafied/validation_context.py
schemafied/validators.py
schemafied/fields/__init__.py
schemafied/fields/base.py
schemafied/fields/dict.py
schemafied/fields/list.py
schemafied/fields/number.py
schemafied/fields/string.py
schemafied-1.0.0.dist-info/licenses/LICENSE
schemafied-1.0.0.dist-info/METADATA
schemafied-1.0.0.dist-info/WHEEL
schemafied-1.0.0.dist-info/top_level.txt
schemafied-1.0.0.dist-info/RECORD
