Metadata-Version: 2.4
Name: schemafied
Version: 1.0.0
Summary: A Python library for validating data structures against user-defined schemas with comprehensive error reporting and nested structure support.
Author-email: Nadeem Ashraf <dev.nadeemashraf06@gmail.com>
License: MIT
Project-URL: Homepage, https://github.com/devnadeemashraf/schemafied
Project-URL: Bug Tracker, https://github.com/devnadeemashraf/schemafied/issues
Project-URL: Documentation, https://github.com/devnadeemashraf/schemafied#readme
Project-URL: Source Code, https://github.com/devnadeemashraf/schemafied
Project-URL: Changelog, https://github.com/devnadeemashraf/schemafied/blob/main/CHANGELOG.md
Keywords: validation,schema,dictionary,data-validation,json-validation,validation-library,python,nested-validation,error-handling,type-checking
Classifier: Development Status :: 4 - Beta
Classifier: Intended Audience :: Developers
Classifier: Operating System :: OS Independent
Classifier: License :: OSI Approved :: MIT License
Classifier: Programming Language :: Python :: 3.13
Classifier: Programming Language :: Python :: 3 :: Only
Classifier: Topic :: Software Development :: Libraries :: Python Modules
Classifier: Topic :: Software Development :: Quality Assurance
Classifier: Topic :: Utilities
Classifier: Typing :: Typed
Classifier: Natural Language :: English
Requires-Python: >=3.13
License-File: LICENSE
Provides-Extra: dev
Requires-Dist: pytest>=8.3.5; extra == "dev"
Requires-Dist: pytest-cov>=6.1.1; extra == "dev"
Requires-Dist: black>=25.1.0; extra == "dev"
Requires-Dist: flake8>=7.2.0; extra == "dev"
Requires-Dist: mypy>=1.15.0; extra == "dev"
Requires-Dist: coverage>=7.8.2; extra == "dev"
Provides-Extra: docs
Requires-Dist: sphinx>=8.2.3; extra == "docs"
Requires-Dist: sphinx-rtd-theme>=3.0.2; extra == "docs"
Requires-Dist: myst-parser>=4.0.1; extra == "docs"
Provides-Extra: build
Requires-Dist: wheel>=0.45.1; extra == "build"
Requires-Dist: build>=1.2.2.post1; extra == "build"
Requires-Dist: twine>=6.1.0; extra == "build"
Requires-Dist: setuptools>=80.9.0; extra == "build"
Provides-Extra: all
Requires-Dist: pytest>=8.3.5; extra == "all"
Requires-Dist: pytest-cov>=6.1.1; extra == "all"
Requires-Dist: black>=25.1.0; extra == "all"
Requires-Dist: flake8>=7.2.0; extra == "all"
Requires-Dist: mypy>=1.15.0; extra == "all"
Requires-Dist: coverage>=7.8.2; extra == "all"
Requires-Dist: sphinx>=8.2.3; extra == "all"
Requires-Dist: sphinx-rtd-theme>=3.0.2; extra == "all"
Requires-Dist: myst-parser>=4.0.1; extra == "all"
Requires-Dist: wheel>=0.45.1; extra == "all"
Requires-Dist: build>=1.2.2.post1; extra == "all"
Requires-Dist: twine>=6.1.0; extra == "all"
Requires-Dist: setuptools>=80.9.0; extra == "all"
Provides-Extra: test
Requires-Dist: pytest>=8.3.5; extra == "test"
Requires-Dist: pytest-cov>=6.1.1; extra == "test"
Requires-Dist: coverage>=7.8.2; extra == "test"
Dynamic: license-file
